odoo/addons/stock_location_children/README.rst
odoo/addons/stock_location_children/__init__.py
odoo/addons/stock_location_children/__manifest__.py
odoo/addons/stock_location_children/i18n/fr.po
odoo/addons/stock_location_children/i18n/it.po
odoo/addons/stock_location_children/i18n/stock_location_children.pot
odoo/addons/stock_location_children/models/__init__.py
odoo/addons/stock_location_children/models/stock_location.py
odoo/addons/stock_location_children/readme/CONTRIBUTORS.md
odoo/addons/stock_location_children/readme/DESCRIPTION.md
odoo/addons/stock_location_children/readme/USAGE.md
odoo/addons/stock_location_children/static/description/children.png
odoo/addons/stock_location_children/static/description/icon.png
odoo/addons/stock_location_children/static/description/index.html
odoo/addons/stock_location_children/tests/__init__.py
odoo/addons/stock_location_children/tests/test_stock_location_children.py
odoo/addons/stock_location_children/views/stock_location.xml
odoo_addon_stock_location_children-18.0.1.0.0.3.dist-info/METADATA
odoo_addon_stock_location_children-18.0.1.0.0.3.dist-info/WHEEL
odoo_addon_stock_location_children-18.0.1.0.0.3.dist-info/top_level.txt
odoo_addon_stock_location_children-18.0.1.0.0.3.dist-info/RECORD
